lcdoc/WebsiteGenerator.py
lcdoc/__init__.py
lcdoc/cxx.py
lcdoc/cxx_generator.py
lcdoc/cxx_target.py
lcdoc/doc_utils.py
lcdoc/html_generators.py
lcdoc/lcdoc.py
lcdoc/string_utils.py
lcdoc/test.py
lcdoc/test_dict.py
lcdoc/types_a.py
lcdoc-0.0.3.dist-info/LICENSE
lcdoc-0.0.3.dist-info/METADATA
lcdoc-0.0.3.dist-info/WHEEL
lcdoc-0.0.3.dist-info/top_level.txt
lcdoc-0.0.3.dist-info/RECORD
