Metadata-Version: 2.1
Name: lcdoc
Version: 0.0.3
Summary: LC documentation generator
Home-page: https://github.com/pypa/sampleproject
Author: Luca Ciucci
Author-email: develop@lucaciucci99.com
License: UNKNOWN
Project-URL: Bug Tracker, https://https://github.com/LucaCiucci/lcdoc/issues
Platform: UNKNOWN
Classifier: Programming Language :: Python :: 3
Classifier: License :: OSI Approved :: MIT License
Classifier: Operating System :: OS Independent
Requires-Python: >=3.6
License-File: LICENSE
